{
    "keep": {
        "days": true,
        "amount": 14
    },
    "auditLog": "C:\\PH-Next\\assignment8\\logs\\winston\\errors\\.1d2c82e362831ff0b75c3b37f54d886e4de517d3-audit.json",
    "files": [
        {
            "date": 1693504387565,
            "name": "C:\\PH-Next\\assignment8\\logs\\winston\\errors\\phu-2023-31-08-23-error.log",
            "hash": "da7e6671addaf4de985d780edc1d6d3f6274129c9def3ad974a45cded0a5b380"
        },
        {
            "date": 1693505113600,
            "name": "C:\\PH-Next\\assignment8\\logs\\winston\\errors\\phu-2023-01-09-00-error.log",
            "hash": "60fab4e0a63ae064f06d483644922aca0a2dd194fab36e55ef8928c0c736de62"
        },
        {
            "date": 1693508567328,
            "name": "C:\\PH-Next\\assignment8\\logs\\winston\\errors\\phu-2023-01-09-01-error.log",
            "hash": "50fac5e8bdcda91a05c4562f3ea4541196ee71170f0cb59b20dfae221d32d737"
        },
        {
            "date": 1693512395660,
            "name": "C:\\PH-Next\\assignment8\\logs\\winston\\errors\\phu-2023-01-09-02-error.log",
            "hash": "6305af0218cfaee2b1ec2b25af0f1310328dfb55c2bfbedb3e654883bcdf1166"
        },
        {
            "date": 1693515603245,
            "name": "C:\\PH-Next\\assignment8\\logs\\winston\\errors\\phu-2023-01-09-03-error.log",
            "hash": "7695310663785775698c62c524b675def6d610d054c35c0ba10f7ba881867d79"
        },
        {
            "date": 1693545036627,
            "name": "C:\\PH-Next\\assignment8\\logs\\winston\\errors\\phu-2023-01-09-11-error.log",
            "hash": "184d786299c40446180a404b95c8a555e7c48c65c6780ce10bbcb5b2d92cac4f"
        },
        {
            "date": 1693549403146,
            "name": "C:\\PH-Next\\assignment8\\logs\\winston\\errors\\phu-2023-01-09-12-error.log",
            "hash": "cc88f9f86111c86480213100cd058694d36a7f9a9829251f34451d28a4ed59e2"
        }
    ],
    "hashType": "sha256"
}